anusuya_package_testing/__init__.py
anusuya_package_testing/greet.py
anusuya_package_testing-0.1.7.dist-info/METADATA
anusuya_package_testing-0.1.7.dist-info/WHEEL
anusuya_package_testing-0.1.7.dist-info/top_level.txt
anusuya_package_testing-0.1.7.dist-info/RECORD
