Metadata-Version: 2.4
Name: anusuya_package_testing
Version: 0.1.7
Summary: A simple Python package for greeting
Classifier: Programming Language :: Python :: 3
Classifier: License :: OSI Approved :: MIT License
Classifier: Operating System :: OS Independent
Requires-Python: >=3.6
Dynamic: classifier
Dynamic: requires-python
Dynamic: summary
